libterraform/__init__.py
libterraform/cli.py
libterraform/common.py
libterraform/config.py
libterraform/exceptions.py
libterraform/libterraform.so
libterraform-0.8.0.dist-info/LICENSE.txt
libterraform-0.8.0.dist-info/METADATA
libterraform-0.8.0.dist-info/WHEEL
libterraform-0.8.0.dist-info/RECORD
